MANIFEST.in
README.rst
setup.py
webpay/__init__.py
webpay/account.py
webpay/charge.py
webpay/customer.py
webpay/data_types.py
webpay/error.py
webpay/error_response.py
webpay/event.py
webpay/recursion.py
webpay/shop.py
webpay/token.py
webpay/webpay.py
webpay.egg-info/PKG-INFO
webpay.egg-info/SOURCES.txt
webpay.egg-info/dependency_links.txt
webpay.egg-info/requires.txt
webpay.egg-info/top_level.txt